emailchecker/__init__.py
emailchecker/main.py
emailchecker-1.3.0.dist-info/METADATA
emailchecker-1.3.0.dist-info/WHEEL
emailchecker-1.3.0.dist-info/entry_points.txt
emailchecker-1.3.0.dist-info/top_level.txt
emailchecker-1.3.0.dist-info/RECORD
